nf_parser/__init__.py
nf_parser/constructs/__init__.py
nf_parser/grammer/nf.lark
nf_parser/parser.py
nf_parser/transformers/__init__.py
nf_parser/transformers/nextflow.py
nf_parser/utils.py
nf_parser-0.0.1.dist-info/LICENSE
nf_parser-0.0.1.dist-info/METADATA
nf_parser-0.0.1.dist-info/WHEEL
nf_parser-0.0.1.dist-info/RECORD
