Metadata-Version: 2.1
Name: nf_parser
Version: 0.0.1
Summary: parse and inspect nextflow DSL scripts to pythonic structures and more. 
License: MIT
Author: obonyojimmy
Author-email: cliffjimmy27@gmail.com
Requires-Python: >=3.9,<4.0
Classifier: License :: OSI Approved :: MIT License
Classifier: Programming Language :: Python :: 3
Classifier: Programming Language :: Python :: 3.9
Classifier: Programming Language :: Python :: 3.10
Classifier: Programming Language :: Python :: 3.11
Classifier: Programming Language :: Python :: 3.12
Requires-Dist: lark (==1.1.5)
Requires-Dist: pydantic (>=1.10.2,<2.0.0)
